intellifire4py/__init__.py
intellifire4py/cloud_api.py
intellifire4py/cloud_interface.py
intellifire4py/const.py
intellifire4py/control.py
intellifire4py/exceptions.py
intellifire4py/local_api.py
intellifire4py/model.py
intellifire4py/py.typed
intellifire4py/read.py
intellifire4py/udp.py
intellifire4py/unified_fireplace.py
intellifire4py/utils.py
intellifire4py-4.2.1.dist-info/METADATA
intellifire4py-4.2.1.dist-info/WHEEL
intellifire4py-4.2.1.dist-info/entry_points.txt
intellifire4py-4.2.1.dist-info/licenses/LICENSE
intellifire4py-4.2.1.dist-info/RECORD
