Metadata-Version: 2.4
Name: intellifire4py
Version: 4.2.1
Summary: Intellifire4Py
Project-URL: Homepage, https://github.com/jeeftor/intellifire4py
Project-URL: Repository, https://github.com/jeeftor/intellifire4py
Project-URL: Documentation, https://intellifire4py.readthedocs.io
Project-URL: Bug Tracker, https://github.com/jeeftor/intellifire4py/issues
Project-URL: Changelog, https://github.com/jeeftor/intellifire4py/releases
Author-email: Jeff Stein <jeffstein@gmail.com>
License: MIT
License-File: LICENSE
Classifier: Development Status :: 5 - Production/Stable
Classifier: Programming Language :: Python :: 3
Classifier: Programming Language :: Python :: 3.11
Classifier: Programming Language :: Python :: 3.12
Classifier: Programming Language :: Python :: 3.13
Requires-Python: >=3.13
Requires-Dist: aenum>=3.1.11
Requires-Dist: aiohttp>=3.9.1
Requires-Dist: pydantic>=1.10.8
Requires-Dist: rich>=10.0.0
Provides-Extra: dev
Requires-Dist: aioresponses>=0.7.6; extra == 'dev'
Requires-Dist: build>=1.0.0; extra == 'dev'
Requires-Dist: codespell>=2.4.1; extra == 'dev'
Requires-Dist: furo>=2024.8.6; extra == 'dev'
Requires-Dist: mypy>=1.5.1; extra == 'dev'
Requires-Dist: myst-parser>=2.0.0; extra == 'dev'
Requires-Dist: nox>=2023.4.22; extra == 'dev'
Requires-Dist: pre-commit-hooks==4.5.0; extra == 'dev'
Requires-Dist: pre-commit>=3.4.0; extra == 'dev'
Requires-Dist: pytest-asyncio>=0.21.1; extra == 'dev'
Requires-Dist: pytest-cov>=4.1.0; extra == 'dev'
Requires-Dist: pytest-mock>=3.14.0; extra == 'dev'
Requires-Dist: pytest-timeout>=2.3.1; extra == 'dev'
Requires-Dist: pytest-xdist>=3.5.0; extra == 'dev'
Requires-Dist: pytest>=7.4.2; extra == 'dev'
Requires-Dist: pyupgrade>=3.13.0; extra == 'dev'
Requires-Dist: ruff>=0.1.4; extra == 'dev'
Requires-Dist: safety>=3.3.1; extra == 'dev'
Requires-Dist: sphinx-autobuild>=2021.3.14; extra == 'dev'
Requires-Dist: sphinx-click>=5.0.1; extra == 'dev'
Requires-Dist: sphinx-copybutton>=0.5.2; extra == 'dev'
Requires-Dist: sphinx>=7.2.6; extra == 'dev'
Requires-Dist: twine>=4.0.0; extra == 'dev'
Requires-Dist: typeguard>=4.1.5; extra == 'dev'
Requires-Dist: uv>=0.8.10; extra == 'dev'
Requires-Dist: xdoctest>=1.1.1; extra == 'dev'
